Metadata-Version: 2.1
Name: khemlib
Version: 0.1.0
Summary: my second library
Home-page: UNKNOWN
Author: Me
License: MIT
Platform: UNKNOWN
